ikwilnaarhuis/__init__.py
ikwilnaarhuis/_version.py
ikwilnaarhuis/cli.py
ikwilnaarhuis-0.0.0.4.24.dist-info/AUTHORS.rst
ikwilnaarhuis-0.0.0.4.24.dist-info/LICENSE.txt
ikwilnaarhuis-0.0.0.4.24.dist-info/METADATA
ikwilnaarhuis-0.0.0.4.24.dist-info/WHEEL
ikwilnaarhuis-0.0.0.4.24.dist-info/entry_points.txt
ikwilnaarhuis-0.0.0.4.24.dist-info/top_level.txt
ikwilnaarhuis-0.0.0.4.24.dist-info/RECORD
