Metadata-Version: 2.1
Name: ikwilnaarhuis
Version: 0.0.0.4.24
Summary: something
Home-page: https://pyscaffold.org/
Author: Lucas Selfslagh
Author-email: lucas.selfslagh@gmail.com
License: mit
Platform: any
Classifier: Development Status :: 4 - Beta
Classifier: Programming Language :: Python
Requires-Dist: pyinsults (>=0.0.0.0.12)
Requires-Dist: colorama
Requires-Dist: termcolor
Requires-Dist: pyfiglet
Provides-Extra: testing
Requires-Dist: pytest (>=4.2.1) ; extra == 'testing'
Requires-Dist: pytest-cov ; extra == 'testing'
